Project Folder/ReRAM_On_FPGA/ReRAM_On_FPGA.srcs/sources_1/new/twin_range_sar_adc.v
`timescale 1ns / 1ps

module twin_range_sar_adc(
    input clk,
    input start,
    input [11:0] analog_input,
    output reg [7:0] digital_out,
    output reg done
);

// Internal registers initialized at declaration (good!)
reg busy = 0;
reg [1:0] phase = 0; // 0=idle, 1=coarse, 2=fine
reg [3:0] bit_count = 0;
reg [11:0] coarse_result = 0;
reg [11:0] fine_result = 0;
reg [11:0] dac_value = 0;

// ******************************************************
// CORRECTED: Declare 'current_bit_weight' at the module level
reg [11:0] current_bit_weight;
// ******************************************************

// Initialize ALL output registers (and any other uninitialized internal regs if applicable)
initial begin
    digital_out = 0;
    done = 0;
    // It's good practice to list all initializations here, even if already done at declaration
    busy = 0;
    phase = 0;
    bit_count = 0;
    coarse_result = 0;
    fine_result = 0;
    dac_value = 0;
    current_bit_weight = 0; // Initialize the new register as well
end

// Threshold for coarse/fine phase (1.0V equivalent)
parameter THRESHOLD = 12'd2048;

// Main state machine
always @(posedge clk) begin
    // Default assignments
    done <= 0; // This will make 'done' go high for only one cycle
    
    if (start && !busy) begin
        // Start new conversion
        busy <= 1;
        bit_count <= 0;
        coarse_result <= 0; // Clear previous result for a new conversion
        fine_result <= 0;   // Clear previous result for a new conversion
        digital_out <= 0;   // Clear output at start of new conversion
        
        // Determine phase
        if (analog_input > THRESHOLD) begin
            phase <= 1; // Coarse phase
            // For coarse phase, we're trying to determine bits 11-4 (8 bits total, where bit 11 is implicit 1)
            // The first trial will be for bit 10 (value 2048).
            dac_value <= 12'b1000_0000_0000; // Start with MSB for coarse search (2048)
        end else begin
            phase <= 2; // Fine phase
            // For fine phase, we're trying to determine bits 11-5 (7 bits from fine, plus 0 as MSB)
            // The first trial will be for bit 10 (value 1024)
            dac_value <= 12'b0100_0000_0000; // Start with MSB for fine search (1024)
        end
    end 
    else if (busy) begin
        if (bit_count < 12) begin // Still converting
            // SAR conversion logic:
            // This is the core of how SAR works:
            // 1. Try to set the current bit (add its weight to dac_value).
            // 2. Compare this new dac_value with analog_input.
            // 3. If trial dac_value is <= analog_input, keep the bit.
            // 4. If trial dac_value is > analog_input, discard the bit (undo the addition).
            
            // Calculate the weight of the current bit we are trying to determine
            // This line is now an assignment, not a declaration, which is allowed.
            if (phase == 1) begin // Coarse phase, starts from 11th bit (MSB) downwards
                current_bit_weight = (12'b1 << (11 - bit_count));
            end else begin // Fine phase, starts from 11th bit (MSB) downwards
                current_bit_weight = (12'b1 << (11 - bit_count));
            end

            // Try adding the current bit weight to the DAC value
            if ((dac_value | current_bit_weight) <= analog_input) begin
                // If adding this bit doesn't exceed analog_input, keep it.
                // This means the current bit is '1'.
                dac_value <= dac_value | current_bit_weight;
            end else begin
                // If adding this bit makes it too high, then this bit is '0'.
                // The dac_value remains unchanged (we don't add this bit).
                dac_value <= dac_value; // Explicitly showing no change
            end
            
            bit_count <= bit_count + 1; // Move to the next bit
        end
        else begin // Conversion for this phase is complete (bit_count is 12)
            busy <= 0; // ADC is no longer busy
            done <= 1; // Signal that conversion is done for one cycle

            // Assign the final digital_out based on the phase and the determined dac_value
            if (phase == 1) begin
                digital_out <= {1'b1, dac_value[10:4]};
            end else begin
                digital_out <= {1'b0, dac_value[10:4]};
            end
        end
    end
end

endmodule

Project Folder/ReRAM_On_FPGA/ReRAM_On_FPGA.srcs/sim_1/new/tb_twin_range_sar_adc.v
`timescale 1ns / 1ps

module tb_twin_range_sar_adc;

// Parameters
reg clk;
reg start;
reg [11:0] analog_input;
wire [7:0] digital_out;
wire done;

// Instantiate DUT
twin_range_sar_adc uut (
    .clk(clk),
    .start(start),
    .analog_input(analog_input),
    .digital_out(digital_out),
    .done(done)
);

// Clock Generation (100 MHz)
always #5 clk = ~clk;

// Main test sequence
initial begin
    // Initialize all signals driven by the testbench at time 0
    clk = 0;
    start = 0;
    analog_input = 0;
    
    // Give some time for initial conditions to settle
    // This #100 also allows the clock to start toggling for 10 cycles
    #100; 
    
    // Monitoring: Now that signals are initialized, $monitor will show valid values
    $monitor("TIME=%0t: START=%b DONE=%b DOUT=%h (Analog_Input=%d)",  // Added analog_input to monitor
              $time, start, done, digital_out, analog_input);
    
    $display("\n=== Starting Testbench Simulation ===");
    
    // --- Test Case 1: Fine Conversion --- //
    $display("\n=== Starting Fine Conversion Test ===");
    analog_input = 12'd1024;  // Represents an input voltage
    start = 1;
    #10 start = 0;
    
    // Wait for conversion to finish, with a 1us timeout
    fork
        begin
            @(posedge done); // Wait for done to go high
        end
        begin
            #1000; // Timeout delay (1000ns = 1us)
            $display("ERROR: Timeout waiting for fine conversion at TIME=%0t!", $time);
            $finish;
        end
    join
    
    $display("Fine Conversion Complete: Input=%d, Output=%d (0x%h)",
              analog_input, digital_out, digital_out);
    
    #100; // Small delay between test cases
    
    // --- Test Case 2: Coarse Conversion --- //
    $display("\n=== Starting Coarse Conversion Test ===");
    analog_input = 12'd3000;  // Represents a different input voltage
    start = 1;
    #10 start = 0;
    
    // Wait for conversion to finish, with a 1us timeout
    fork
        begin
            @(posedge done); // Wait for done to go high
        end
        begin
            #1000; // Timeout delay
            $display("ERROR: Timeout waiting for coarse conversion at TIME=%0t!", $time);
            $finish;
        end
    join
    
    $display("Coarse Conversion Complete: Input=%d, Output=%d (0x%h)",
              analog_input, digital_out, digital_out);
    
    #100; // Small delay at the end
    $display("\nAll tests completed successfully!");
    $finish;
end

// Waveform dump (for debugging)
initial begin
    $dumpfile("adc_sim.vcd");
    $dumpvars(0, tb_twin_range_sar_adc);
end

endmodule

Project Folder/ReRAM_On_FPGA/ReRAM_On_FPGA.sim/sim_1/behav/xsim/adc_sim.vcd
$date
   Thu Jun 12 12:26:54 2025
$end
$version
  2018.1
$end
$timescale
  1ps
$end
$scope module tb_twin_range_sar_adc $end
$var reg 1 ! clk $end
$var reg 1 " start $end
$var reg 12 # analog_input [11:0] $end
$var wire 8 $ digital_out [7:0] $end
$var wire 1 % done $end
$scope module uut $end
$var wire 1 & clk $end
$var wire 1 ' start $end
$var wire 12 ( analog_input [11:0] $end
$var reg 8 ) digital_out [7:0] $end
$var reg 1 * done $end
$var reg 1 + busy $end
$var reg 2 , phase [1:0] $end
$var reg 4 - bit_count [3:0] $end
$var reg 12 . coarse_result [11:0] $end
$var reg 12 / fine_result [11:0] $end
$var reg 12 0 dac_value [11:0] $end
$var reg 12 1 current_bit_weight [11:0] $end
$var parameter 12 2 THRESHOLD [11:0] $end
$upscope $end
$upscope $end
$enddefinitions $end
#0
$dumpvars
0!
0"
b0 #
b0 $
0%
0&
0'
b0 (
b0 )
0*
0+
b0 ,
b0 -
b0 .
b0 /
b0 0
b0 1
b100000000000 2
$end
#5000
1!
1&
#10000
0!
0&
#15000
1!
1&
#20000
0!
0&
#25000
1!
1&
#30000
0!
0&
#35000
1!
1&
#40000
0!
0&
#45000
1!
1&
#50000
0!
0&
#55000
1!
1&
#60000
0!
0&
#65000
1!
1&
#70000
0!
0&
#75000
1!
1&
#80000
0!
0&
#85000
1!
1&
#90000
0!
0&
#95000
1!
1&
#100000
0!
1"
b10000000000 #
0&
1'
b10000000000 (
#105000
1!
1&
b0 )
1+
b10 ,
b10000000000 0
#110000
0!
0"
0&
0'
#115000
1!
1&
b1 -
b100000000000 1
#120000
0!
0&
#125000
1!
1&
b10 -
b10000000000 1
#130000
0!
0&
#135000
1!
1&
b11 -
b1000000000 1
#140000
0!
0&
#145000
1!
1&
b100 -
b100000000 1
#150000
0!
0&
#155000
1!
1&
b101 -
b10000000 1
#160000
0!
0&
#165000
1!
1&
b110 -
b1000000 1
#170000
0!
0&
#175000
1!
1&
b111 -
b100000 1
#180000
0!
0&
#185000
1!
1&
b1000 -
b10000 1
#190000
0!
0&
#195000
1!
1&
b1001 -
b1000 1
#200000
0!
0&
#205000
1!
1&
b1010 -
b100 1
#210000
0!
0&
#215000
1!
1&
b1011 -
b10 1
#220000
0!
0&
#225000
1!
1&
b1100 -
b1 1
#230000
0!
0&
#235000
1!
b1000000 $
1%
1&
b1000000 )
1*
0+
#240000
0!
0&
#245000
1!
0%
1&
0*
